h5xxhsum/__init__.py
h5xxhsum/_version.py
h5xxhsum/cli/__init__.py
h5xxhsum-0.1.0.dist-info/METADATA
h5xxhsum-0.1.0.dist-info/WHEEL
h5xxhsum-0.1.0.dist-info/entry_points.txt
h5xxhsum-0.1.0.dist-info/licenses/LICENSE
h5xxhsum-0.1.0.dist-info/RECORD
