Metadata-Version: 2.4
Name: h5xxhsum
Version: 0.1.0
Summary: Compute xxHash digest of hdf5 datasets
Project-URL: Documentation, https://github.com/miccoli/hdf5-xxh?tab=readme-ov-file#readme-ov-file
Project-URL: Issues, https://github.com/miccoli/hdf5-xxh/issues
Project-URL: Source, https://github.com/miccoli/hdf5-xxh.git
Author-email: Stefano Miccoli <stefano.miccoli@polimi.it>
License-Expression: MIT
License-File: LICENSE
Classifier: Development Status :: 3 - Alpha
Classifier: Environment :: Console
Classifier: Programming Language :: Python
Classifier: Programming Language :: Python :: 3.8
Classifier: Programming Language :: Python :: 3.9
Classifier: Programming Language :: Python :: 3.10
Classifier: Programming Language :: Python :: 3.11
Classifier: Programming Language :: Python :: 3.12
Classifier: Programming Language :: Python :: 3.13
Classifier: Programming Language :: Python :: Implementation :: CPython
Requires-Python: >=3.8
Requires-Dist: click>=8.1
Requires-Dist: h5py>=3.11.0
Requires-Dist: xxhash>=3.4.1
